LICENSE
README.md
setup.py
CVE_2023_5089.egg-info/PKG-INFO
CVE_2023_5089.egg-info/SOURCES.txt
CVE_2023_5089.egg-info/dependency_links.txt
CVE_2023_5089.egg-info/entry_points.txt
CVE_2023_5089.egg-info/requires.txt
CVE_2023_5089.egg-info/top_level.txt
cve20235089/__init__.py
cve20235089/main.py
cve20235089/includes/__init__.py
cve20235089/includes/bot.py
cve20235089/includes/filereader.py
cve20235089/includes/scan.py
cve20235089/includes/writefile.py
cve20235089/utils/__init__.py
cve20235089/utils/configure.py
cve20235089/utils/const.py
cve20235089/utils/helpers.py
cve20235089/utils/status.py